odoo9_addon_stock_picking_package_preparation_line-9.0.1.0.0.99.dev25-py3.8-nspkg.pth
odoo_addons/stock_picking_package_preparation_line/README.rst
odoo_addons/stock_picking_package_preparation_line/__init__.py
odoo_addons/stock_picking_package_preparation_line/__openerp__.py
odoo_addons/stock_picking_package_preparation_line/i18n/ar.po
odoo_addons/stock_picking_package_preparation_line/i18n/bg.po
odoo_addons/stock_picking_package_preparation_line/i18n/bs.po
odoo_addons/stock_picking_package_preparation_line/i18n/ca.po
odoo_addons/stock_picking_package_preparation_line/i18n/cs.po
odoo_addons/stock_picking_package_preparation_line/i18n/da.po
odoo_addons/stock_picking_package_preparation_line/i18n/da_DK.po
odoo_addons/stock_picking_package_preparation_line/i18n/de.po
odoo_addons/stock_picking_package_preparation_line/i18n/en.po
odoo_addons/stock_picking_package_preparation_line/i18n/en_GB.po
odoo_addons/stock_picking_package_preparation_line/i18n/es.po
odoo_addons/stock_picking_package_preparation_line/i18n/es_AR.po
odoo_addons/stock_picking_package_preparation_line/i18n/es_CL.po
odoo_addons/stock_picking_package_preparation_line/i18n/es_CO.po
odoo_addons/stock_picking_package_preparation_line/i18n/es_CR.po
odoo_addons/stock_picking_package_preparation_line/i18n/es_DO.po
odoo_addons/stock_picking_package_preparation_line/i18n/es_EC.po
odoo_addons/stock_picking_package_preparation_line/i18n/es_MX.po
odoo_addons/stock_picking_package_preparation_line/i18n/es_PE.po
odoo_addons/stock_picking_package_preparation_line/i18n/es_PY.po
odoo_addons/stock_picking_package_preparation_line/i18n/es_VE.po
odoo_addons/stock_picking_package_preparation_line/i18n/et.po
odoo_addons/stock_picking_package_preparation_line/i18n/eu.po
odoo_addons/stock_picking_package_preparation_line/i18n/fa.po
odoo_addons/stock_picking_package_preparation_line/i18n/fi.po
odoo_addons/stock_picking_package_preparation_line/i18n/fr.po
odoo_addons/stock_picking_package_preparation_line/i18n/gl.po
odoo9_addon_stock_picking_package_preparation_line-9.0.1.0.0.99.dev25.dist-info/METADATA
odoo9_addon_stock_picking_package_preparation_line-9.0.1.0.0.99.dev25.dist-info/WHEEL
odoo9_addon_stock_picking_package_preparation_line-9.0.1.0.0.99.dev25.dist-info/namespace_packages.txt
odoo9_addon_stock_picking_package_preparation_line-9.0.1.0.0.99.dev25.dist-info/top_level.txt
odoo9_addon_stock_picking_package_preparation_line-9.0.1.0.0.99.dev25.dist-info/RECORD
